{
    "type": "FeatureCollection",
    "features": [
        {
            "type": "Feature",
            "properties": {
                "name": "WCT_ELP_BRR_to_Reston",
                "time": "2013-10-26T14:12:03.45Z",
                "coordTimes": [
                    "2013-10-26T14:12:03.45Z",
                    "2013-10-26T14:12:04.05Z",
                    "2013-10-26T14:12:05.47Z",
                    "2013-10-26T14:12:06.59Z",
                    "2013-10-26T14:12:06.71Z",
                    "2013-10-26T14:12:08.09Z",
                    "2013-10-26T14:12:08.97Z",
                    "2013-10-26T14:12:09.99Z",
                    "2013-10-26T14:12:11.13Z",
                    "2013-10-26T14:12:12.38Z",
                    "2013-10-26T14:12:13.68Z",
                    "2013-10-26T14:12:14.85Z",
                    "2013-10-26T14:12:16.18Z",
                    "2013-10-26T14:12:16.64Z",
                    "2013-10-26T14:12:17.96Z",
                    "2013-10-26T14:12:19.08Z",
                    "2013-10-26T14:12:19.70Z",
                    "2013-10-26T14:12:20.96Z",
                    "2013-10-26T14:12:22.16Z",
                    "2013-10-26T14:12:23.31Z",
                    "2013-10-26T14:12:23.40Z",
                    "2013-10-26T14:12:24.44Z",
                    "2013-10-26T14:12:25.46Z",
                    "2013-10-26T14:12:26.36Z",
                    "2013-10-26T14:12:26.89Z",
                    "2013-10-26T14:12:27.26Z",
                    "2013-10-26T14:12:27.49Z",
                    "2013-10-26T14:12:27.71Z",
                    "2013-10-26T14:12:28.50Z",
                    "2013-10-26T14:12:28.62Z",
                    "2013-10-26T14:12:29.55Z",
                    "2013-10-26T14:12:30.51Z",
                    "2013-10-26T14:12:30.85Z",
                    "2013-10-26T14:12:31.43Z",
                    "2013-10-26T14:12:31.97Z",
                    "2013-10-26T14:12:32.64Z",
                    "2013-10-26T14:12:33.55Z",
                    "2013-10-26T14:12:34.62Z",
                    "2013-10-26T14:12:35Z",
                    "2013-10-26T14:12:35.74Z",
                    "2013-10-26T14:12:36.10Z",
                    "2013-10-26T14:12:36.75Z",
                    "2013-10-26T14:12:37.35Z",
                    "2013-10-26T14:12:37.82Z",
                    "2013-10-26T14:12:38.07Z",
                    "2013-10-26T14:12:38.81Z",
                    "2013-10-26T14:12:39.03Z",
                    "2013-10-26T14:12:39.53Z",
                    "2013-10-26T14:12:40.60Z",
                    "2013-10-26T14:12:41.11Z",
                    "2013-10-26T14:12:41.84Z",
                    "2013-10-26T14:12:42.94Z",
                    "2013-10-26T14:12:44.16Z",
                    "2013-10-26T14:12:45.35Z",
                    "2013-10-26T14:12:45.64Z",
                    "2013-10-26T14:12:46.47Z",
                    "2013-10-26T14:12:46.84Z",
                    "2013-10-26T14:12:47.39Z",
                    "2013-10-26T14:12:47.89Z",
                    "2013-10-26T14:12:48.76Z",
                    "2013-10-26T14:12:49.32Z",
                    "2013-10-26T14:12:49.74Z",
                    "2013-10-26T14:12:50.06Z",
                    "2013-10-26T14:12:51.03Z",
                    "2013-10-26T14:12:52.36Z",
                    "2013-10-26T14:12:53.45Z",
                    "2013-10-26T14:12:54.55Z",
                    "2013-10-26T14:12:54.87Z",
                    "2013-10-26T14:12:55.40Z",
                    "2013-10-26T14:12:56.66Z",
                    "2013-10-26T14:12:56.86Z",
                    "2013-10-26T14:12:57.96Z",
                    "2013-10-26T14:12:58.43Z",
                    "2013-10-26T14:12:58.94Z",
                    "2013-10-26T14:13:00.18Z",
                    "2013-10-26T14:13:00.44Z",
                    "2013-10-26T14:13:01.24Z",
                    "2013-10-26T14:13:01.62Z",
                    "2013-10-26T14:13:02.76Z",
                    "2013-10-26T14:13:02.91Z",
                    "2013-10-26T14:13:03.51Z",
                    "2013-10-26T14:13:04.58Z",
                    "2013-10-26T14:13:04.72Z",
                    "2013-10-26T14:13:05.29Z",
                    "2013-10-26T14:13:05.88Z",
                    "2013-10-26T14:13:07.07Z",
                    "2013-10-26T14:13:07.65Z",
                    "2013-10-26T14:13:08.74Z",
                    "2013-10-26T14:13:09.79Z",
                    "2013-10-26T14:13:10.78Z",
                    "2013-10-26T14:13:11.58Z",
                    "2013-10-26T14:13:11.89Z",
                    "2013-10-26T14:13:12.59Z",
                    "2013-10-26T14:13:12.79Z",
                    "2013-10-26T14:13:13.33Z",
                    "2013-10-26T14:13:14.61Z",
                    "2013-10-26T14:13:15.39Z",
                    "2013-10-26T14:13:16.35Z",
                    "2013-10-26T14:13:16.64Z",
                    "2013-10-26T14:13:16.96Z",
                    "2013-10-26T14:13:17.51Z",
                    "2013-10-26T14:13:18.49Z",
                    "2013-10-26T14:13:19.53Z",
                    "2013-10-26T14:13:20.70Z",
                    "2013-10-26T14:13:21.40Z",
                    "2013-10-26T14:13:21.94Z",
                    "2013-10-26T14:13:22.35Z",
                    "2013-10-26T14:13:22.94Z",
                    "2013-10-26T14:13:24.13Z",
                    "2013-10-26T14:13:24.29Z",
                    "2013-10-26T14:13:25.43Z",
                    "2013-10-26T14:13:25.57Z",
                    "2013-10-26T14:13:26.06Z",
                    "2013-10-26T14:13:26.93Z",
                    "2013-10-26T14:13:27.57Z",
                    "2013-10-26T14:13:28.50Z",
                    "2013-10-26T14:13:28.59Z",
                    "2013-10-26T14:13:28.73Z",
                    "2013-10-26T14:13:29.80Z",
                    "2013-10-26T14:13:30.10Z",
                    "2013-10-26T14:13:30.59Z",
                    "2013-10-26T14:13:31.61Z",
                    "2013-10-26T14:13:32.66Z",
                    "2013-10-26T14:13:33.55Z",
                    "2013-10-26T14:13:34.54Z",
                    "2013-10-26T14:13:34.85Z",
                    "2013-10-26T14:13:35.75Z",
                    "2013-10-26T14:13:36.25Z",
                    "2013-10-26T14:13:36.60Z",
                    "2013-10-26T14:13:36.85Z",
                    "2013-10-26T14:13:37.36Z",
                    "2013-10-26T14:13:37.97Z",
                    "2013-10-26T14:13:38.67Z",
                    "2013-10-26T14:13:39.20Z",
                    "2013-10-26T14:13:39.32Z",
                    "2013-10-26T14:13:39.85Z",
                    "2013-10-26T14:13:40.02Z",
                    "2013-10-26T14:13:40.69Z",
                    "2013-10-26T14:13:41.68Z",
                    "2013-10-26T14:13:41.81Z",
                    "2013-10-26T14:13:42.04Z",
                    "2013-10-26T14:13:42.46Z",
                    "2013-10-26T14:13:42.79Z",
                    "2013-10-26T14:13:42.90Z",
                    "2013-10-26T14:13:43.48Z",
                    "2013-10-26T14:13:44.25Z",
                    "2013-10-26T14:13:45.15Z",
                    "2013-10-26T14:13:46.14Z",
                    "2013-10-26T14:13:47Z",
                    "2013-10-26T14:13:47.87Z",
                    "2013-10-26T14:13:48.22Z",
                    "2013-10-26T14:13:49.55Z",
                    "2013-10-26T14:13:51.19Z",
                    "2013-10-26T14:13:52.98Z",
                    "2013-10-26T14:13:54.33Z",
                    "2013-10-26T14:13:55.66Z",
                    "2013-10-26T14:13:55.72Z",
                    "2013-10-26T14:13:56.88Z",
                    "2013-10-26T14:13:57.35Z",
                    "2013-10-26T14:13:58.22Z",
                    "2013-10-26T14:13:58.41Z",
                    "2013-10-26T14:13:58.86Z",
                    "2013-10-26T14:13:59.92Z",
                    "2013-10-26T14:14:01.01Z",
                    "2013-10-26T14:14:02.11Z",
                    "2013-10-26T14:14:02.96Z",
                    "2013-10-26T14:14:04.25Z",
                    "2013-10-26T14:14:04.69Z",
                    "2013-10-26T14:14:05.59Z",
                    "2013-10-26T14:14:06.43Z",
                    "2013-10-26T14:14:06.88Z",
                    "2013-10-26T14:14:07.90Z",
                    "2013-10-26T14:14:08.31Z",
                    "2013-10-26T14:14:09.52Z",
                    "2013-10-26T14:14:10.80Z",
                    "2013-10-26T14:14:11.72Z",
                    "2013-10-26T14:14:12.82Z",
                    "2013-10-26T14:14:14.01Z",
                    "2013-10-26T14:14:14.61Z",
                    "2013-10-26T14:14:15.15Z",
                    "2013-10-26T14:14:16.03Z",
                    "2013-10-26T14:14:17.03Z",
                    "2013-10-26T14:14:17.74Z",
                    "2013-10-26T14:14:19Z",
                    "2013-10-26T14:14:19.70Z",
                    "2013-10-26T14:14:20.93Z",
                    "2013-10-26T14:14:21.67Z",
                    "2013-10-26T14:14:22.52Z",
                    "2013-10-26T14:14:23.62Z",
                    "2013-10-26T14:14:23.94Z",
                    "2013-10-26T14:14:24.12Z",
                    "2013-10-26T14:14:24.47Z",
                    "2013-10-26T14:14:25.56Z",
                    "2013-10-26T14:14:26.54Z",
                    "2013-10-26T14:14:26.69Z",
                    "2013-10-26T14:14:27.28Z",
                    "2013-10-26T14:14:27.57Z",
                    "2013-10-26T14:14:28.18Z",
                    "2013-10-26T14:14:28.41Z",
                    "2013-10-26T14:14:28.81Z",
                    "2013-10-26T14:14:29.72Z",
                    "2013-10-26T14:14:30.66Z",
                    "2013-10-26T14:14:31.65Z",
                    "2013-10-26T14:14:32.04Z",
                    "2013-10-26T14:14:32.35Z",
                    "2013-10-26T14:14:32.73Z",
                    "2013-10-26T14:14:33.53Z",
                    "2013-10-26T14:14:34.42Z",
                    "2013-10-26T14:14:34.56Z",
                    "2013-10-26T14:14:35.67Z",
                    "2013-10-26T14:14:36.78Z",
                    "2013-10-26T14:14:37.79Z",
                    "2013-10-26T14:14:37.88Z",
                    "2013-10-26T14:14:38.46Z",
                    "2013-10-26T14:14:39.43Z",
                    "2013-10-26T14:14:40.27Z",
                    "2013-10-26T14:14:40.64Z",
                    "2013-10-26T14:14:41.15Z",
                    "2013-10-26T14:14:41.88Z",
                    "2013-10-26T14:14:43.12Z",
                    "2013-10-26T14:14:43.32Z",
                    "2013-10-26T14:14:43.67Z",
                    "2013-10-26T14:14:44.87Z",
                    "2013-10-26T14:14:44.96Z",
                    "2013-10-26T14:14:45.54Z",
                    "2013-10-26T14:14:45.96Z",
                    "2013-10-26T14:14:46.30Z",
                    "2013-10-26T14:14:47.24Z",
                    "2013-10-26T14:14:48.23Z",
                    "2013-10-26T14:14:48.65Z",
                    "2013-10-26T14:14:49.71Z",
                    "2013-10-26T14:14:49.88Z",
                    "2013-10-26T14:14:50.36Z",
                    "2013-10-26T14:14:51.28Z",
                    "2013-10-26T14:14:52.23Z",
                    "2013-10-26T14:14:52.55Z",
                    "2013-10-26T14:14:53.32Z",
                    "2013-10-26T14:14:54.30Z",
                    "2013-10-26T14:14:54.46Z",
                    "2013-10-26T14:14:55.65Z",
                    "2013-10-26T14:14:55.95Z",
                    "2013-10-26T14:14:56.31Z",
                    "2013-10-26T14:14:56.79Z",
                    "2013-10-26T14:14:56.99Z",
                    "2013-10-26T14:14:57.17Z",
                    "2013-10-26T14:14:57.34Z",
                    "2013-10-26T14:14:58.25Z",
                    "2013-10-26T14:14:59.29Z",
                    "2013-10-26T14:14:59.46Z",
                    "2013-10-26T14:14:59.65Z",
                    "2013-10-26T14:15:00.99Z",
                    "2013-10-26T14:15:02.05Z",
                    "2013-10-26T14:15:03.27Z",
                    "2013-10-26T14:15:03.73Z",
                    "2013-10-26T14:15:04.59Z",
                    "2013-10-26T14:15:05.67Z",
                    "2013-10-26T14:15:06.17Z",
                    "2013-10-26T14:15:07.53Z",
                    "2013-10-26T14:15:08.46Z",
                    "2013-10-26T14:15:08.75Z",
                    "2013-10-26T14:15:10.31Z",
                    "2013-10-26T14:15:11.85Z",
                    "2013-10-26T14:15:12.11Z",
                    "2013-10-26T14:15:12.95Z",
                    "2013-10-26T14:15:14.37Z",
                    "2013-10-26T14:15:15.66Z",
                    "2013-10-26T14:15:16.62Z",
                    "2013-10-26T14:15:17.71Z",
                    "2013-10-26T14:15:18.78Z",
                    "2013-10-26T14:15:19.26Z",
                    "2013-10-26T14:15:20.13Z",
                    "2013-10-26T14:15:21.28Z",
                    "2013-10-26T14:15:21.66Z",
                    "2013-10-26T14:15:21.83Z",
                    "2013-10-26T14:15:23.26Z",
                    "2013-10-26T14:15:24.47Z",
                    "2013-10-26T14:15:25.50Z",
                    "2013-10-26T14:15:26.06Z",
                    "2013-10-26T14:15:27.35Z",
                    "2013-10-26T14:15:28.23Z",
                    "2013-10-26T14:15:29.25Z",
                    "2013-10-26T14:15:30.46Z"
                ]
            },
            "geometry": {
                "type": "LineString",
                "coordinates": [
                    [
                        -77.377624,
                        38.888716,
                        154.43
                    ],
                    [
                        -77.377498,
                        38.888721,
                        153.95
                    ],
                    [
                        -77.377246,
                        38.888837,
                        154.91
                    ],
                    [
                        -77.377229,
                        38.889018,
                        152.99
                    ],
                    [
                        -77.377233,
                        38.889036,
                        153.47
                    ],
                    [
                        -77.377065,
                        38.889215,
                        152.51
                    ],
                    [
                        -77.376967,
                        38.889335,
                        151.06
                    ],
                    [
                        -77.37693,
                        38.889497,
                        150.1
                    ],
                    [
                        -77.376871,
                        38.889673,
                        150.1
                    ],
                    [
                        -77.37674,
                        38.889847,
                        151.06
                    ],
                    [
                        -77.376553,
                        38.889998,
                        151.54
                    ],
                    [
                        -77.37636,
                        38.890111,
                        151.06
                    ],
                    [
                        -77.376123,
                        38.89022,
                        150.58
                    ],
                    [
                        -77.376043,
                        38.890258,
                        149.62
                    ],
                    [
                        -77.375812,
                        38.890373,
                        149.14
                    ],
                    [
                        -77.375605,
                        38.890453,
                        148.18
                    ],
                    [
                        -77.375499,
                        38.89051,
                        147.7
                    ],
                    [
                        -77.375277,
                        38.890614,
                        147.22
                    ],
                    [
                        -77.375069,
                        38.890721,
                        146.74
                    ],
                    [
                        -77.374881,
                        38.890834,
                        148.18
                    ],
                    [
                        -77.374878,
                        38.890847,
                        147.22
                    ],
                    [
                        -77.375016,
                        38.890977,
                        145.3
                    ],
                    [
                        -77.375107,
                        38.891125,
                        143.37
                    ],
                    [
                        -77.374982,
                        38.891231,
                        141.93
                    ],
                    [
                        -77.374876,
                        38.891255,
                        141.93
                    ],
                    [
                        -77.374812,
                        38.891287,
                        143.85
                    ],
                    [
                        -77.374766,
                        38.891296,
                        141.45
                    ],
                    [
                        -77.374729,
                        38.891315,
                        140.49
                    ],
                    [
                        -77.374568,
                        38.891336,
                        140.01
                    ],
                    [
                        -77.37455,
                        38.891351,
                        140.01
                    ],
                    [
                        -77.374391,
                        38.891433,
                        140.01
                    ],
                    [
                        -77.374271,
                        38.891557,
                        139.05
                    ],
                    [
                        -77.374247,
                        38.891609,
                        137.13
                    ],
                    [
                        -77.374134,
                        38.891639,
                        136.16
                    ],
                    [
                        -77.374079,
                        38.891714,
                        135.2
                    ],
                    [
                        -77.373957,
                        38.891767,
                        135.2
                    ],
                    [
                        -77.373809,
                        38.891857,
                        134.24
                    ],
                    [
                        -77.373647,
                        38.891973,
                        132.32
                    ],
                    [
                        -77.373574,
                        38.891998,
                        132.32
                    ],
                    [
                        -77.373422,
                        38.891999,
                        131.36
                    ],
                    [
                        -77.373347,
                        38.892002,
                        131.36
                    ],
                    [
                        -77.373216,
                        38.891982,
                        130.88
                    ],
                    [
                        -77.373092,
                        38.891978,
                        130.4
                    ],
                    [
                        -77.372995,
                        38.891969,
                        130.88
                    ],
                    [
                        -77.372943,
                        38.891969,
                        130.4
                    ],
                    [
                        -77.372793,
                        38.891944,
                        130.4
                    ],
                    [
                        -77.372749,
                        38.891943,
                        129.92
                    ],
                    [
                        -77.37265,
                        38.891918,
                        130.4
                    ],
                    [
                        -77.372446,
                        38.891984,
                        130.4
                    ],
                    [
                        -77.372349,
                        38.892015,
                        128.95
                    ],
                    [
                        -77.372211,
                        38.891966,
                        129.92
                    ],
                    [
                        -77.371999,
                        38.8919,
                        130.88
                    ],
                    [
                        -77.371792,
                        38.891787,
                        130.88
                    ],
                    [
                        -77.37157,
                        38.891708,
                        130.88
                    ],
                    [
                        -77.371519,
                        38.891683,
                        130.88
                    ],
                    [
                        -77.371348,
                        38.891672,
                        129.43
                    ],
                    [
                        -77.371283,
                        38.891705,
                        129.43
                    ],
                    [
                        -77.371186,
                        38.891749,
                        128.95
                    ],
                    [
                        -77.371108,
                        38.891802,
                        128.47
                    ],
                    [
                        -77.370974,
                        38.891895,
                        127.99
                    ],
                    [
                        -77.370896,
                        38.891962,
                        127.99
                    ],
                    [
                        -77.370809,
                        38.891956,
                        127.51
                    ],
                    [
                        -77.370744,
                        38.891955,
                        127.51
                    ],
                    [
                        -77.370543,
                        38.891954,
                        127.51
                    ],
                    [
                        -77.370309,
                        38.892068,
                        127.51
                    ],
                    [
                        -77.370106,
                        38.892141,
                        127.03
                    ],
                    [
                        -77.369885,
                        38.892183,
                        127.03
                    ],
                    [
                        -77.369823,
                        38.892202,
                        127.03
                    ],
                    [
                        -77.369725,
                        38.892239,
                        126.07
                    ],
                    [
                        -77.369536,
                        38.89238,
                        125.59
                    ],
                    [
                        -77.3695,
                        38.892396,
                        126.07
                    ],
                    [
                        -77.369282,
                        38.892348,
                        126.55
                    ],
                    [
                        -77.369187,
                        38.892365,
                        126.07
                    ],
                    [
                        -77.369083,
                        38.892378,
                        126.07
                    ],
                    [
                        -77.368834,
                        38.892328,
                        126.07
                    ],
                    [
                        -77.36878,
                        38.892323,
                        125.59
                    ],
                    [
                        -77.368616,
                        38.892328,
                        126.07
                    ],
                    [
                        -77.368542,
                        38.892346,
                        126.55
                    ],
                    [
                        -77.36831,
                        38.892387,
                        125.59
                    ],
                    [
                        -77.368283,
                        38.892397,
                        126.07
                    ],
                    [
                        -77.36816,
                        38.892405,
                        126.07
                    ],
                    [
                        -77.367987,
                        38.892512,
                        124.63
                    ],
                    [
                        -77.367967,
                        38.892529,
                        125.11
                    ],
                    [
                        -77.367871,
                        38.892582,
                        125.59
                    ],
                    [
                        -77.367804,
                        38.892661,
                        125.59
                    ],
                    [
                        -77.36762,
                        38.892788,
                        125.59
                    ],
                    [
                        -77.36753,
                        38.89285,
                        124.15
                    ],
                    [
                        -77.367401,
                        38.892993,
                        124.63
                    ],
                    [
                        -77.367353,
                        38.893159,
                        125.11
                    ],
                    [
                        -77.367239,
                        38.893291,
                        126.07
                    ],
                    [
                        -77.367175,
                        38.89341,
                        124.63
                    ],
                    [
                        -77.367138,
                        38.893451,
                        124.63
                    ],
                    [
                        -77.367043,
                        38.893535,
                        124.63
                    ],
                    [
                        -77.367011,
                        38.893555,
                        125.11
                    ],
                    [
                        -77.366931,
                        38.893616,
                        124.63
                    ],
                    [
                        -77.366754,
                        38.893768,
                        123.19
                    ],
                    [
                        -77.366619,
                        38.893837,
                        123.67
                    ],
                    [
                        -77.36643,
                        38.893885,
                        122.71
                    ],
                    [
                        -77.366373,
                        38.8939,
                        122.22
                    ],
                    [
                        -77.366309,
                        38.893914,
                        122.71
                    ],
                    [
                        -77.36621,
                        38.893871,
                        123.19
                    ],
                    [
                        -77.366014,
                        38.89383,
                        122.71
                    ],
                    [
                        -77.365818,
                        38.893764,
                        122.22
                    ],
                    [
                        -77.365621,
                        38.893653,
                        122.22
                    ],
                    [
                        -77.365524,
                        38.89357,
                        122.71
                    ],
                    [
                        -77.365414,
                        38.89359,
                        122.71
                    ],
                    [
                        -77.365358,
                        38.893638,
                        123.19
                    ],
                    [
                        -77.365256,
                        38.893691,
                        122.22
                    ],
                    [
                        -77.365056,
                        38.893804,
                        121.74
                    ],
                    [
                        -77.365024,
                        38.893809,
                        121.26
                    ],
                    [
                        -77.364837,
                        38.893921,
                        120.78
                    ],
                    [
                        -77.364808,
                        38.893919,
                        121.26
                    ],
                    [
                        -77.364712,
                        38.893943,
                        121.26
                    ],
                    [
                        -77.364631,
                        38.894067,
                        121.26
                    ],
                    [
                        -77.364592,
                        38.894166,
                        120.78
                    ],
                    [
                        -77.364459,
                        38.894275,
                        119.82
                    ],
                    [
                        -77.364446,
                        38.894283,
                        120.3
                    ],
                    [
                        -77.364418,
                        38.894292,
                        120.3
                    ],
                    [
                        -77.364241,
                        38.894394,
                        121.74
                    ],
                    [
                        -77.364189,
                        38.894421,
                        121.26
                    ],
                    [
                        -77.364114,
                        38.894475,
                        120.3
                    ],
                    [
                        -77.363939,
                        38.894567,
                        118.86
                    ],
                    [
                        -77.363739,
                        38.894631,
                        117.9
                    ],
                    [
                        -77.363614,
                        38.894738,
                        117.9
                    ],
                    [
                        -77.363575,
                        38.894894,
                        117.42
                    ],
                    [
                        -77.363595,
                        38.89494,
                        117.9
                    ],
                    [
                        -77.3636,
                        38.895085,
                        117.42
                    ],
                    [
                        -77.363634,
                        38.895161,
                        117.42
                    ],
                    [
                        -77.363563,
                        38.895165,
                        116.46
                    ],
                    [
                        -77.363573,
                        38.895204,
                        115.98
                    ],
                    [
                        -77.36365,
                        38.895261,
                        115.98
                    ],
                    [
                        -77.363594,
                        38.89535,
                        117.9
                    ],
                    [
                        -77.363454,
                        38.895376,
                        117.9
                    ],
                    [
                        -77.363346,
                        38.895386,
                        118.86
                    ],
                    [
                        -77.363322,
                        38.895383,
                        119.34
                    ],
                    [
                        -77.363214,
                        38.895367,
                        118.86
                    ],
                    [
                        -77.363181,
                        38.895378,
                        118.86
                    ],
                    [
                        -77.363042,
                        38.895384,
                        118.38
                    ],
                    [
                        -77.362842,
                        38.895418,
                        119.34
                    ],
                    [
                        -77.362816,
                        38.895418,
                        119.82
                    ],
                    [
                        -77.362769,
                        38.895414,
                        119.82
                    ],
                    [
                        -77.362812,
                        38.895353,
                        118.86
                    ],
                    [
                        -77.362775,
                        38.89531,
                        118.86
                    ],
                    [
                        -77.362756,
                        38.8953,
                        118.38
                    ],
                    [
                        -77.362667,
                        38.895236,
                        117.42
                    ],
                    [
                        -77.362582,
                        38.895132,
                        116.46
                    ],
                    [
                        -77.362547,
                        38.894989,
                        116.46
                    ],
                    [
                        -77.362505,
                        38.894834,
                        116.94
                    ],
                    [
                        -77.362462,
                        38.8947,
                        118.38
                    ],
                    [
                        -77.362423,
                        38.894563,
                        119.34
                    ],
                    [
                        -77.362408,
                        38.894507,
                        119.34
                    ],
                    [
                        -77.362341,
                        38.8943,
                        120.78
                    ],
                    [
                        -77.362164,
                        38.894074,
                        120.78
                    ],
                    [
                        -77.36184,
                        38.893936,
                        120.78
                    ],
                    [
                        -77.361572,
                        38.893874,
                        119.82
                    ],
                    [
                        -77.361321,
                        38.893791,
                        118.38
                    ],
                    [
                        -77.361311,
                        38.893784,
                        118.38
                    ],
                    [
                        -77.361082,
                        38.893729,
                        117.42
                    ],
                    [
                        -77.360996,
                        38.893692,
                        116.94
                    ],
                    [
                        -77.36082,
                        38.893722,
                        115.01
                    ],
                    [
                        -77.360787,
                        38.893736,
                        114.05
                    ],
                    [
                        -77.360711,
                        38.893778,
                        114.53
                    ],
                    [
                        -77.360633,
                        38.893938,
                        113.09
                    ],
                    [
                        -77.360516,
                        38.894088,
                        113.09
                    ],
                    [
                        -77.36039,
                        38.894235,
                        113.57
                    ],
                    [
                        -77.360337,
                        38.894366,
                        113.09
                    ],
                    [
                        -77.36026,
                        38.894565,
                        113.57
                    ],
                    [
                        -77.360263,
                        38.894635,
                        113.57
                    ],
                    [
                        -77.360229,
                        38.894777,
                        114.53
                    ],
                    [
                        -77.360217,
                        38.894913,
                        113.57
                    ],
                    [
                        -77.360238,
                        38.894982,
                        113.57
                    ],
                    [
                        -77.360184,
                        38.895141,
                        113.57
                    ],
                    [
                        -77.360152,
                        38.895203,
                        114.05
                    ],
                    [
                        -77.360027,
                        38.895371,
                        114.05
                    ],
                    [
                        -77.359886,
                        38.895545,
                        114.53
                    ],
                    [
                        -77.359761,
                        38.895657,
                        114.05
                    ],
                    [
                        -77.359644,
                        38.89581,
                        114.05
                    ],
                    [
                        -77.359531,
                        38.895978,
                        115.01
                    ],
                    [
                        -77.359447,
                        38.89605,
                        115.01
                    ],
                    [
                        -77.359345,
                        38.896086,
                        115.5
                    ],
                    [
                        -77.359176,
                        38.896139,
                        115.5
                    ],
                    [
                        -77.358997,
                        38.896221,
                        116.46
                    ],
                    [
                        -77.358872,
                        38.896278,
                        115.98
                    ],
                    [
                        -77.358705,
                        38.896434,
                        115.01
                    ],
                    [
                        -77.358667,
                        38.896542,
                        114.53
                    ],
                    [
                        -77.358594,
                        38.896732,
                        114.53
                    ],
                    [
                        -77.358554,
                        38.896848,
                        113.09
                    ],
                    [
                        -77.358521,
                        38.896982,
                        112.13
                    ],
                    [
                        -77.358397,
                        38.89713,
                        111.65
                    ],
                    [
                        -77.358355,
                        38.897168,
                        113.57
                    ],
                    [
                        -77.358332,
                        38.897192,
                        114.53
                    ],
                    [
                        -77.35829,
                        38.897238,
                        115.98
                    ],
                    [
                        -77.358113,
                        38.897346,
                        116.94
                    ],
                    [
                        -77.357941,
                        38.89743,
                        115.98
                    ],
                    [
                        -77.357916,
                        38.897444,
                        115.98
                    ],
                    [
                        -77.357819,
                        38.897503,
                        115.01
                    ],
                    [
                        -77.357777,
                        38.897536,
                        114.53
                    ],
                    [
                        -77.357668,
                        38.897583,
                        113.57
                    ],
                    [
                        -77.357632,
                        38.897607,
                        113.57
                    ],
                    [
                        -77.357563,
                        38.897644,
                        113.09
                    ],
                    [
                        -77.357388,
                        38.8977,
                        112.61
                    ],
                    [
                        -77.357203,
                        38.897742,
                        111.65
                    ],
                    [
                        -77.357025,
                        38.897822,
                        111.17
                    ],
                    [
                        -77.356993,
                        38.897879,
                        111.17
                    ],
                    [
                        -77.356939,
                        38.897852,
                        111.65
                    ],
                    [
                        -77.356878,
                        38.897813,
                        111.65
                    ],
                    [
                        -77.356745,
                        38.897738,
                        111.17
                    ],
                    [
                        -77.356573,
                        38.897682,
                        111.17
                    ],
                    [
                        -77.356553,
                        38.897667,
                        111.65
                    ],
                    [
                        -77.35636,
                        38.897572,
                        111.17
                    ],
                    [
                        -77.356131,
                        38.897583,
                        111.65
                    ],
                    [
                        -77.355926,
                        38.897551,
                        110.21
                    ],
                    [
                        -77.355911,
                        38.897541,
                        110.21
                    ],
                    [
                        -77.355814,
                        38.897487,
                        110.69
                    ],
                    [
                        -77.355635,
                        38.897416,
                        110.69
                    ],
                    [
                        -77.355463,
                        38.897407,
                        110.69
                    ],
                    [
                        -77.355386,
                        38.897408,
                        110.21
                    ],
                    [
                        -77.355286,
                        38.897382,
                        110.21
                    ],
                    [
                        -77.355147,
                        38.897337,
                        109.73
                    ],
                    [
                        -77.354902,
                        38.897399,
                        109.25
                    ],
                    [
                        -77.354863,
                        38.897392,
                        109.25
                    ],
                    [
                        -77.354808,
                        38.897354,
                        110.21
                    ],
                    [
                        -77.354611,
                        38.897238,
                        110.69
                    ],
                    [
                        -77.354593,
                        38.89724,
                        109.73
                    ],
                    [
                        -77.354473,
                        38.89723,
                        109.73
                    ],
                    [
                        -77.354385,
                        38.897223,
                        109.73
                    ],
                    [
                        -77.354322,
                        38.897202,
                        110.21
                    ],
                    [
                        -77.354158,
                        38.897119,
                        109.73
                    ],
                    [
                        -77.353954,
                        38.897123,
                        110.21
                    ],
                    [
                        -77.353867,
                        38.89712,
                        109.25
                    ],
                    [
                        -77.353651,
                        38.897093,
                        110.21
                    ],
                    [
                        -77.353616,
                        38.897093,
                        110.21
                    ],
                    [
                        -77.353517,
                        38.897102,
                        110.21
                    ],
                    [
                        -77.35333,
                        38.897079,
                        109.73
                    ],
                    [
                        -77.353134,
                        38.897086,
                        109.73
                    ],
                    [
                        -77.353076,
                        38.897112,
                        109.73
                    ],
                    [
                        -77.352994,
                        38.897218,
                        109.73
                    ],
                    [
                        -77.352875,
                        38.897346,
                        109.73
                    ],
                    [
                        -77.352843,
                        38.89735,
                        110.21
                    ],
                    [
                        -77.352845,
                        38.897543,
                        110.69
                    ],
                    [
                        -77.352901,
                        38.897561,
                        110.21
                    ],
                    [
                        -77.352862,
                        38.897512,
                        110.69
                    ],
                    [
                        -77.35284,
                        38.897437,
                        110.21
                    ],
                    [
                        -77.352803,
                        38.897455,
                        111.65
                    ],
                    [
                        -77.352789,
                        38.89748,
                        111.17
                    ],
                    [
                        -77.352762,
                        38.897498,
                        111.17
                    ],
                    [
                        -77.352845,
                        38.89763,
                        110.69
                    ],
                    [
                        -77.352962,
                        38.897769,
                        110.69
                    ],
                    [
                        -77.352981,
                        38.897794,
                        111.17
                    ],
                    [
                        -77.353003,
                        38.897819,
                        110.21
                    ],
                    [
                        -77.353189,
                        38.897977,
                        110.69
                    ],
                    [
                        -77.3533,
                        38.898125,
                        111.17
                    ],
                    [
                        -77.353411,
                        38.898301,
                        112.13
                    ],
                    [
                        -77.353462,
                        38.898363,
                        112.61
                    ],
                    [
                        -77.353566,
                        38.898476,
                        113.09
                    ],
                    [
                        -77.353619,
                        38.898644,
                        113.57
                    ],
                    [
                        -77.353608,
                        38.898725,
                        115.01
                    ],
                    [
                        -77.353724,
                        38.898923,
                        115.01
                    ],
                    [
                        -77.353817,
                        38.899054,
                        115.98
                    ],
                    [
                        -77.353853,
                        38.899093,
                        115.98
                    ],
                    [
                        -77.354012,
                        38.899311,
                        116.46
                    ],
                    [
                        -77.354169,
                        38.899527,
                        117.9
                    ],
                    [
                        -77.354201,
                        38.899561,
                        119.82
                    ],
                    [
                        -77.354288,
                        38.899677,
                        119.34
                    ],
                    [
                        -77.354433,
                        38.899875,
                        120.3
                    ],
                    [
                        -77.354568,
                        38.900054,
                        119.34
                    ],
                    [
                        -77.354659,
                        38.900193,
                        121.26
                    ],
                    [
                        -77.354785,
                        38.900337,
                        122.22
                    ],
                    [
                        -77.354901,
                        38.900484,
                        123.67
                    ],
                    [
                        -77.354954,
                        38.900549,
                        123.19
                    ],
                    [
                        -77.355088,
                        38.900644,
                        124.63
                    ],
                    [
                        -77.355229,
                        38.900793,
                        125.11
                    ],
                    [
                        -77.35526,
                        38.900849,
                        125.59
                    ],
                    [
                        -77.355282,
                        38.900869,
                        125.11
                    ],
                    [
                        -77.355398,
                        38.901081,
                        126.55
                    ],
                    [
                        -77.355529,
                        38.901246,
                        127.03
                    ],
                    [
                        -77.355612,
                        38.9014,
                        127.51
                    ],
                    [
                        -77.355703,
                        38.901454,
                        127.51
                    ],
                    [
                        -77.355813,
                        38.901643,
                        127.99
                    ],
                    [
                        -77.355896,
                        38.90177,
                        127.51
                    ],
                    [
                        -77.356014,
                        38.901905,
                        127.51
                    ],
                    [
                        -77.356076,
                        38.902094,
                        126.55
                    ]
                ]
            }
        }
    ]
}